Metadata-Version: 2.1
Name: tfinputfn
Version: 2.0.0
Summary: An input function for tensorflow. 
Home-page: UNKNOWN
Author: Vijay Satheesh
Author-email: vijayskk007@gmail.com
License: MIT
Keywords: tensorflow
Platform: UNKNOWN
Classifier: Development Status :: 5 - Production/Stable
Classifier: Intended Audience :: Developers
Classifier: Operating System :: MacOS
Classifier: License :: OSI Approved :: MIT License
Classifier: Programming Language :: Python :: 3
License-File: LICENCE.txt
